magic_number_guess/__init__.py
magic_number_guess/game.py
magic_number_guess-1.0.0.dist-info/LICENSE
magic_number_guess-1.0.0.dist-info/METADATA
magic_number_guess-1.0.0.dist-info/WHEEL
magic_number_guess-1.0.0.dist-info/top_level.txt
magic_number_guess-1.0.0.dist-info/RECORD
