Metadata-Version: 2.1
Name: magic-number-guess
Version: 1.0.0
Summary: A magical number guessing game library
Home-page: https://github.com/ybshubham/magic-number-guess
Author: Shubham Yadav
Author-email: yb.shubham@gmail.com
License: UNKNOWN
Platform: UNKNOWN
Requires-Dist: pytest (>=6.2.4)
